api_testing_toolkit/__about__.py
api_testing_toolkit/__init__.py
api_testing_toolkit-1.0.0.dist-info/METADATA
api_testing_toolkit-1.0.0.dist-info/WHEEL
api_testing_toolkit-1.0.0.dist-info/licenses/LICENSE.txt
api_testing_toolkit-1.0.0.dist-info/RECORD
