Metadata-Version: 2.3
Name: api-testing-toolkit
Version: 1.0.0
Summary: A set of functions to facilitate API testing with jupyter lab.
Project-URL: Documentation, https://github.com/Belkonar/api-testing-toolkit#readme
Project-URL: Issues, https://github.com/Belkonar/api-testing-toolkit/issues
Project-URL: Source, https://github.com/Belkonar/api-testing-toolkit
Author: Tom
License-Expression: MIT
License-File: LICENSE.txt
Classifier: Development Status :: 4 - Beta
Classifier: Framework :: Jupyter :: JupyterLab
Classifier: License :: OSI Approved :: MIT License
Classifier: Programming Language :: Python
Classifier: Programming Language :: Python :: 3.8
Classifier: Programming Language :: Python :: 3.9
Classifier: Programming Language :: Python :: 3.10
Classifier: Programming Language :: Python :: 3.11
Classifier: Programming Language :: Python :: 3.12
Classifier: Programming Language :: Python :: Implementation :: CPython
Classifier: Programming Language :: Python :: Implementation :: PyPy
Requires-Python: >=3.8
Requires-Dist: jupyterlab>=4.2.3
Requires-Dist: requests>=2.32.3
